setup.cfg
setup.py
pmod/__init__.py
pmod/pmod.py
pmod.egg-info/PKG-INFO
pmod.egg-info/SOURCES.txt
pmod.egg-info/dependency_links.txt
pmod.egg-info/top_level.txt