Metadata-Version: 1.0
Name: pmod
Version: 0.2.1
Summary: A personal package for personal use. Use for anyone is allowed.
Home-page: https://github.com/ShadowPerson/pmod
Author: InTheShadows
Author-email: paolocastro128@gmail.com
License: UNKNOWN
Platform: UNKNOWN
